<?xml version='1.0' encoding='UTF-8'?><entry xmlns="http://www.w3.org/2005/Atom" xmlns:as="http://atomserver.org/namespaces/1.0/"><id>/electron/atom/v1/domesday/pages-NI-26-35/NI-264000-351000-17.xml</id><title type="text"> Entry: pages-NI-26-35 NI-264000-351000-17</title><author><name>AtomServer APP Service</name></author><link href="/electron/atom/v1/domesday/pages-NI-26-35/NI-264000-351000-17.xml" rel="self" /><link href="/electron/atom/v1/domesday/pages-NI-26-35/NI-264000-351000-17.xml/4" rel="edit" /><as:entryId>NI-264000-351000-17</as:entryId><as:updateIndex>227237</as:updateIndex><as:revision>3</as:revision><updated>2011-05-01T09:24:05.000Z</updated><published>2011-05-01T09:17:36.000Z</published><content type="application/xml"><page xmlns="">
		<dblock_id>NI-264000-351000</dblock_id>
		<year>1986</year>
		<title>17A'cloy United Football Club</title>
		<content> Since 1965 when Aughnacloy senior     
 football team ceased to exist the{    
{Moutray Memorial Cup},presented by the
{Moutray Family}of{Favour Royal}to the 
 British Legion, has been played for,  
 by teams of under 16 years. Although  
 in previous years,up to{11 teams}have 
 taken part, this year only{4}have     
 entered. The cup is held by the       
 winning team for{one year}and all     
 matches must be played on home ground,
 that is in Aughnacloy,at the{Secondary
{School Playing Fields}. As well as the
 winning team receiving the cup,each   
 member is presented with a medal.The  
 chairman of the club,{Mr. Mervyn      
{McKeown,}is assisted by{Kenneth Givan 
 a former player himself.It is hoped   
 that by the end of June the winning   
 team will have been decided.          
                                       
                                       </content>
	</page></content></entry>