<?xml version='1.0' encoding='UTF-8'?><entry xmlns="http://www.w3.org/2005/Atom" xmlns:as="http://atomserver.org/namespaces/1.0/"><id>/electron/atom/v1/domesday/dblocks-GB-51-35/GB-512000-354000.xml</id><title type="text"> Entry: dblocks-GB-51-35 GB-512000-354000</title><author><name>AtomServer APP Service</name></author><link href="/electron/atom/v1/domesday/dblocks-GB-51-35/GB-512000-354000.xml" rel="self" /><link href="/electron/atom/v1/domesday/dblocks-GB-51-35/GB-512000-354000.xml/8" rel="edit" /><as:entryId>GB-512000-354000</as:entryId><as:updateIndex>397423</as:updateIndex><as:revision>7</as:revision><updated>2011-05-11T00:01:40.000Z</updated><published>2011-05-10T23:53:30.000Z</published><content type="application/xml"><dblock xmlns="">
		<dblock_id>GB-512000-354000</dblock_id>
		<lat>53.071177474764</lat>
		<long>-0.32813024138023</long>
		<bounds>53.071942005045 -0.32900181452938 53.071121461852 -0.27156561194685 53.096728544115 -0.27053939723678 53.097549846576 -0.32800966694027 53.071942005045 -0.32900181452938</bounds>
	</dblock></content></entry>