<?xml version='1.0' encoding='UTF-8'?><entry xmlns="http://www.w3.org/2005/Atom" xmlns:as="http://atomserver.org/namespaces/1.0/"><id>/electron/atom/v1/domesday/pages-GB-16-18/GB-168000-18000-13.xml</id><title type="text"> Entry: pages-GB-16-18 GB-168000-18000-13</title><author><name>AtomServer APP Service</name></author><link href="/electron/atom/v1/domesday/pages-GB-16-18/GB-168000-18000-13.xml" rel="self" /><link href="/electron/atom/v1/domesday/pages-GB-16-18/GB-168000-18000-13.xml/3" rel="edit" /><as:entryId>GB-168000-18000-13</as:entryId><as:updateIndex>130295</as:updateIndex><as:revision>2</as:revision><updated>2011-04-30T10:29:09.000Z</updated><published>2011-04-30T10:23:02.000Z</published><content type="application/xml"><page xmlns="">
		<dblock_id>GB-168000-18000</dblock_id>
		<year>1986</year>
		<title>13GOONHILLY NATURE RESERVE</title>
		<content>{PLANT LIST contd.}                    
 Milkwort,Heath      Rush,Bulbous      
 Moor-grass,Purple   Rush,Compact      
 Mouse-ear,Common    Rush,Dwarf        
 Mouse-ear,Sea       Rush,Pygmy        
 Mustard,Black       Rush,Sea          
 Navelwort          Rush,Sharp-flowered
 Orchid,Fragrant     Sage,Wood         
 Parsley-piert     St.John's-wort,Marsh
 Pearlwort,Heath     St.John's-wort,   
 Pearlwort,Fringed              Slender
 Pennywort,Wall(=Navelwort) Sandwort,  
 Pimpernel,Bog                  Spring 
 Pimpernel,Scarlet    Saw-wort         
 Plantain,Buck's-horn Scabious,Devil's 
 Plantain,Ribwort                 -bit 
 Plantain,Sea       Scurvy-grass,Danish
 Primrose            Sedge,Bottle      
 Privet,Wild         Sedge,Carnation   
 Restharrow,Common   Sedge,Flea        
 Rose,Burnet         Sedge,Glaucous    
 Rupturewort,Fringed Sedge,Green-ribbed</content>
	</page></content></entry>