<?xml version='1.0' encoding='UTF-8'?><entry xmlns="http://www.w3.org/2005/Atom" xmlns:as="http://atomserver.org/namespaces/1.0/"><id>/electron/atom/v1/domesday/pages-GB-38-29/GB-388000-291000-19.xml</id><title type="text"> Entry: pages-GB-38-29 GB-388000-291000-19</title><author><name>AtomServer APP Service</name></author><link href="/electron/atom/v1/domesday/pages-GB-38-29/GB-388000-291000-19.xml" rel="self" /><link href="/electron/atom/v1/domesday/pages-GB-38-29/GB-388000-291000-19.xml/1" rel="edit" /><as:entryId>GB-388000-291000-19</as:entryId><as:updateIndex>165399</as:updateIndex><as:revision>0</as:revision><updated>2011-04-30T19:47:13.000Z</updated><published>2011-04-30T19:47:13.000Z</published><content type="application/xml"><page xmlns="">
		<dblock_id>GB-388000-291000</dblock_id>
		<year>1986</year>
		<title>19A day in my life (2)</title>
		<content>{ Lunchtime}is over and we have{drama.I
 have acting our{Egyptian Topic}work in
 mime.Suddenley the{fire bell}rings,the
{class}goes quickly outside.We are the 
 only ones-is there a{fire?-Oh}dear my 
{teacher}didn't have the{message}about 
 the{bell testing.                     
  Back to{work}and the{bell}goes for   
{home-time.I}go{home}change out of{my  
{uniform,do my homework}and{eat my     
{tea.I read,knit or watch              
{television,until bedtime,at nine      
{o'clock.                              
                                       
                                       
                                       
                                       
                                       
                                       
                                       
                                       
                                       </content>
	</page></content></entry>