<?xml version='1.0' encoding='UTF-8'?><entry xmlns="http://www.w3.org/2005/Atom" xmlns:as="http://atomserver.org/namespaces/1.0/"><id>/electron/atom/v1/domesday/pages-GB-38-20/GB-380000-204000-15.xml</id><title type="text"> Entry: pages-GB-38-20 GB-380000-204000-15</title><author><name>AtomServer APP Service</name></author><link href="/electron/atom/v1/domesday/pages-GB-38-20/GB-380000-204000-15.xml" rel="self" /><link href="/electron/atom/v1/domesday/pages-GB-38-20/GB-380000-204000-15.xml/2" rel="edit" /><as:entryId>GB-380000-204000-15</as:entryId><as:updateIndex>162309</as:updateIndex><as:revision>1</as:revision><updated>2011-04-30T19:45:44.000Z</updated><published>2011-04-30T19:31:22.000Z</published><content type="application/xml"><page xmlns="">
		<dblock_id>GB-380000-204000</dblock_id>
		<year>1986</year>
		<title>15LOCAL NEWS IN WEST STROUD</title>
		<content> The main news story of 1985 in the    
 local newspaper, the Stroud News and  
 Journal, is the story of the          
 meningitis outbreak amongst young     
 children in the area. The new cases   
 have brought the total number to more 
 than 50 since 1980.  Several kind of  
 meningitis have affected children with
 35 of the cases being severe          
 meninococcal meningitis.  Doctors have
 not traced a common root cause to the 
 outbreak of the disease but           
 investigations are still being carried
 out by Stroud Council's Health        
 Committee.  The happiest local news   
 story of 1985 is the £6,000 raised by 
 the local newspaper for the Ethiopian 
 Appeal.                               
                                       
                                       
                                       
                                       </content>
	</page></content></entry>