<?xml version='1.0' encoding='UTF-8'?><entry xmlns="http://www.w3.org/2005/Atom" xmlns:as="http://atomserver.org/namespaces/1.0/"><id>/electron/atom/v1/domesday/pages-GB-43-29/GB-436000-294000-5.xml</id><title type="text"> Entry: pages-GB-43-29 GB-436000-294000-5</title><author><name>AtomServer APP Service</name></author><link href="/electron/atom/v1/domesday/pages-GB-43-29/GB-436000-294000-5.xml" rel="self" /><link href="/electron/atom/v1/domesday/pages-GB-43-29/GB-436000-294000-5.xml/2" rel="edit" /><as:entryId>GB-436000-294000-5</as:entryId><as:updateIndex>338465</as:updateIndex><as:revision>1</as:revision><updated>2011-05-03T16:35:15.000Z</updated><published>2011-05-03T16:29:42.000Z</published><content type="application/xml"><page xmlns="">
		<dblock_id>GB-436000-294000</dblock_id>
		<year>1986</year>
		<title>05ANOTHER COUNTRY HOUSE</title>
		<content>   {Lindley Lodge}now known as{King's  
{Lodge}is situated by the Watling      
 Street near Nuneaton Warwickshire.    
 An old country house surrounded by    
 lawns and trees stands in 13 acres of 
 land.For the past 18 months it has    
 been a{Training School}for the        
{International Missionary Organisation 
 known as{'Youth with a Mission'.      
    The Mission-a charitable Trust-was 
 founded in 1960 and has bases in 60   
 Countries.Students of 18 years upwards
 come from all over the World for short
 or long term studies of the complete  
{Bible and Discipleship}training.Some  
 become overseas Missionaries and      
 others aim to work in City churches.By
 the end of 1985 the Mission hope to   
 own this property.Funds for the       
 Organisation come from support groups 
 around the world.The present Director 
 is Mr Oliver Nyumbu from Zimbabwe.    </content>
	</page></content></entry>