<?xml version='1.0' encoding='UTF-8'?><entry xmlns="http://www.w3.org/2005/Atom" xmlns:as="http://atomserver.org/namespaces/1.0/"><id>/electron/atom/v1/domesday/pages-GB-52-28/GB-528000-282000-2.xml</id><title type="text"> Entry: pages-GB-52-28 GB-528000-282000-2</title><author><name>AtomServer APP Service</name></author><link href="/electron/atom/v1/domesday/pages-GB-52-28/GB-528000-282000-2.xml" rel="self" /><link href="/electron/atom/v1/domesday/pages-GB-52-28/GB-528000-282000-2.xml/1" rel="edit" /><as:entryId>GB-528000-282000-2</as:entryId><as:updateIndex>208659</as:updateIndex><as:revision>0</as:revision><updated>2011-04-30T23:16:44.000Z</updated><published>2011-04-30T23:16:44.000Z</published><content type="application/xml"><page xmlns="">
		<dblock_id>GB-528000-282000</dblock_id>
		<year>1986</year>
		<title>02RECREATION,eating in Bury.</title>
		<content>  Recreation,Wining,Dining,Drinking.   
 The{White Lion}is a popular Public    
 House on Bury Road.It operates normal 
 licensing hours.In the pub there is a 
 restaurant where they sell meals and  
 bar snacks.There is a beer garden.It  
 is patronised by local people and     
 Americans from the Air Force Base in  
 Upwood.The pool,darts and dominoes    
 attract some of the younger           
 generation.They are at their busiest  
 at the weekend.The{Bow Window}is a    
 listed building built in 1460 this    
 makes it medieval.Opening days are    
 Wednesday to Saturday from 7.30 till  
 late ,but it can be hired for private 
 functions.The menu changes every 2    
 months.There are 13 staff,3 full time 
 and 10 part time.As well as local     
 people many foreigners visit the      
 Restaurant.The lives on the           
 premises,and likes the area very much.</content>
	</page></content></entry>