<?xml version='1.0' encoding='UTF-8'?><entry xmlns="http://www.w3.org/2005/Atom" xmlns:as="http://atomserver.org/namespaces/1.0/"><id>/electron/atom/v1/domesday/pages-GB-26-36/GB-260000-366000-8.xml</id><title type="text"> Entry: pages-GB-26-36 GB-260000-366000-8</title><author><name>AtomServer APP Service</name></author><link href="/electron/atom/v1/domesday/pages-GB-26-36/GB-260000-366000-8.xml" rel="self" /><link href="/electron/atom/v1/domesday/pages-GB-26-36/GB-260000-366000-8.xml/1" rel="edit" /><as:entryId>GB-260000-366000-8</as:entryId><as:updateIndex>102997</as:updateIndex><as:revision>0</as:revision><updated>2011-04-30T07:06:32.000Z</updated><published>2011-04-30T07:06:32.000Z</published><content type="application/xml"><page xmlns="">
		<dblock_id>GB-260000-366000</dblock_id>
		<year>1986</year>
		<title>08RECREATION-URDO</title>
		<content>           RECREATION_URDD             
           _______________             
 The "URDD" is the Welsh league of     
 youth and is an organisation that     
 gives us an opportunity to visit camp 
 at GLAN LLYN near BALA.We can join the
 URDD at school and we meet after      
 school to take part in various        
 activities.The things we do include   
 country dancing,orienteering,treasure 
 hunts,film shows,                     
 gymnastics,quiz,discos,drama,talks and
 many more.                            
           Every year we have the      
 NATIONAL EISTEDDFOD when the youth of 
 Wales get together to compete at      
 dancing,singing,recitation,drama,art&amp;c
 raft etc.The EISTEDDFOD will be       
 visiting Bethesda in 1986 and we have 
 already collected about £50,000 to    
 stage it.There will be 1000's of      
 children here then.                   </content>
	</page></content></entry>